LICENSE
README.md
setup.py
jsbuilder/__init__.py
jsbuilder.egg-info/PKG-INFO
jsbuilder.egg-info/SOURCES.txt
jsbuilder.egg-info/dependency_links.txt
jsbuilder.egg-info/requires.txt
jsbuilder.egg-info/top_level.txt