Metadata-Version: 2.1
Name: jsbuilder
Version: 0.1.1
Summary: Convert Python code to JavaScript strings, just by decorating it with @js!
Home-page: https://github.com/tvst/jsbuilder
Author: Thiago Teixeira
Author-email: me@thiagot.com
License: Apache 2
Platform: UNKNOWN
Classifier: Programming Language :: Python :: 3
Classifier: License :: OSI Approved :: Apache Software License
Classifier: Operating System :: OS Independent
Requires-Python: >=3.5
License-File: LICENSE
